{
  "parent": "minecraft:recipes/root",
  "rewards": {
    "recipes": [
      "embellishcraft-bop:cherry_table"
    ]
  },
  "criteria": {
    "has_cherry_slab": {
      "trigger": "minecraft:inventory_changed",
      "conditions": {
        "items": [
          {
            "item": "biomesoplenty:cherry_slab"
          }
        ]
      }
    },
    "has_the_recipe": {
      "trigger": "minecraft:recipe_unlocked",
      "conditions": {
        "recipe": "embellishcraft-bop:cherry_table"
      }
    }
  },
  "requirements": [
    [
      "has_cherry_slab",
      "has_the_recipe"
    ]
  ]
}